nidx_binding/__init__.py
nidx_binding/nidx_binding.cpython-39-x86_64-linux-gnu.so
nidx_binding-6.11.1.post762.dist-info/METADATA
nidx_binding-6.11.1.post762.dist-info/WHEEL
nidx_binding-6.11.1.post762.dist-info/RECORD
