Metadata-Version: 2.4
Name: nidx_binding
Version: 6.11.1.post762
Classifier: Programming Language :: Rust
Classifier: Programming Language :: Python :: Implementation :: CPython
Classifier: Programming Language :: Python :: Implementation :: PyPy
Summary: Bindings for nidx (part of nucliadb)
Author-email: Nuclia <nucliadb@nuclia.com>
License-Expression: AGPL-3.0-or-later
Requires-Python: >=3.10, <4
Project-URL: Homepage, https://nuclia.com
Project-URL: Repository, https://github.com/nuclia/nucliadb
